{
  "_disabled": "false",
  "host": "x86_64-Linux",
  "rank": "",
  "pkg": "mash",
  "pkg_family": "mash",
  "pkg_id": "mash#github.com_dennisbergevin_mash",
  "pkg_name": "mash",
  "pkg_type": "static",
  "pkg_webpage": "https://github.com/dennisbergevin/mash",
  "bundle": "false",
  "category": [
    "Utility"
  ],
  "description": "A customizable command launcher for storing and executing commands",
  "homepage": [
    "https://github.com/dennisbergevin/mash"
  ],
  "license": [
    "MIT"
  ],
  "maintainer": [
    "pkgforge-go (https://github.com/pkgforge-go/builder)"
  ],
  "provides": [
    "mash"
  ],
  "note": [
    "[EXTERNAL] (This is an Official but externally maintained repository)",
    "This package was automatically built from source using go+zig",
    "Provided by: https://github.com/pkgforge-go/builder",
    "Learn More: https://docs.pkgforge.dev/repositories/external/pkgforge-go"
  ],
  "src_url": [
    "https://proxy.golang.org/github.com/dennisbergevin/mash/@v/v0.1.2.zip"
  ],
  "tag": [
    "Utility"
  ],
  "version": "v0.1.2",
  "version_upstream": "",
  "bsum": "c6f92cc6059f11624ee70365e545d4ed14c12036f2195d932abc461a8b26ebd4",
  "build_date": "2025-07-02T10:03:23Z",
  "build_gha": "https://github.com/pkgforge-go/builder/actions/runs/16021952314",
  "build_id": "16021952314",
  "build_log": "https://api.ghcr.pkgforge.dev/pkgforge-go/github/dennisbergevin/mash/mash?tag=v0.1.2-x86_64-Linux&download=mash.log",
  "deprecated": "false",
  "desktop_integration": "false",
  "download_count": "27",
  "download_url": "https://api.ghcr.pkgforge.dev/pkgforge-go/github/dennisbergevin/mash/mash?tag=v0.1.2-x86_64-Linux&download=mash",
  "external": "true",
  "ghcr_pkg": "ghcr.io/pkgforge-go/github/dennisbergevin/mash/mash:v0.1.2-x86_64-Linux",
  "ghcr_url": "https://ghcr.io/pkgforge-go/github/dennisbergevin/mash/mash",
  "installable": "true",
  "manifest_url": "https://api.ghcr.pkgforge.dev/pkgforge-go/github/dennisbergevin/mash/mash?tag=v0.1.2-x86_64-Linux&manifest",
  "portable": "true",
  "recurse_provides": "false",
  "shasum": "bc9f75ce04561216a6035ba11cb8acf9c938ca1cbe3721ffc853d90fdfc8e35b",
  "size": "4.8 MB",
  "size_raw": "4969088",
  "soar_syms": "false",
  "snapshots": [
    "HEAD-fc61991-250621T134333-x86_64-Linux[v0.1.2]"
  ],
  "trusted": "true"
}
