{
  "_disabled": "false",
  "host": "riscv64-Linux",
  "rank": "",
  "pkg": "example",
  "pkg_family": "evo-layout",
  "pkg_id": "example#github.com_GregoryKogan_evo_layout",
  "pkg_name": "example",
  "pkg_type": "static",
  "pkg_webpage": "https://github.com/GregoryKogan/evo-layout",
  "bundle": "false",
  "category": [
    "Utility"
  ],
  "description": "A high-performance, modular Go library for exploring hybrid genetic algorithms _SGA, NSGA-II, SPEA2, FR-NSGA2_ applied to multi-objective graph layout and other optimization problems.",
  "homepage": [
    "https://github.com/GregoryKogan/evo-layout"
  ],
  "license": [
    "MIT"
  ],
  "maintainer": [
    "pkgforge-go (https://github.com/pkgforge-go/builder)"
  ],
  "provides": [
    "example",
    "test"
  ],
  "note": [
    "[EXTERNAL] (This is an Official but externally maintained repository)",
    "This package was automatically built from source using go+zig",
    "Provided by: https://github.com/pkgforge-go/builder",
    "Learn More: https://docs.pkgforge.dev/repositories/external/pkgforge-go"
  ],
  "src_url": [
    "https://github.com/GregoryKogan/evo-layout/archive/1507c087a5f9a3d5de8ed3f45ff72ec9ea36ca90.tar.gz"
  ],
  "tag": [
    "evolutionary-computation",
    "genetic-algorithm",
    "go",
    "golang",
    "graph-drawing",
    "graph-layout",
    "mephi",
    "multi-objective-optimization",
    "nsga-ii",
    "nsga2",
    "optimization-library",
    "research-project",
    "spea2"
  ],
  "version": "HEAD-1507c08-250629T024941",
  "version_upstream": "",
  "bsum": "fbf1e2d70b69192682df604cbf030730f26bed39209862f92f344da036dd37b1",
  "build_date": "2025-06-29T06:57:44Z",
  "build_gha": "https://github.com/pkgforge-go/builder/actions/runs/15952552188",
  "build_id": "15952552188",
  "build_log": "https://api.ghcr.pkgforge.dev/pkgforge-go/github/gregorykogan/evo-layout/example?tag=HEAD-1507c08-250629T024941-riscv64-Linux&download=example.log",
  "deprecated": "false",
  "desktop_integration": "false",
  "download_count": "8",
  "download_url": "https://api.ghcr.pkgforge.dev/pkgforge-go/github/gregorykogan/evo-layout/example?tag=HEAD-1507c08-250629T024941-riscv64-Linux&download=example",
  "external": "true",
  "ghcr_pkg": "ghcr.io/pkgforge-go/github/gregorykogan/evo-layout/example:HEAD-1507c08-250629T024941-riscv64-Linux",
  "ghcr_url": "https://ghcr.io/pkgforge-go/github/gregorykogan/evo-layout/example",
  "installable": "true",
  "manifest_url": "https://api.ghcr.pkgforge.dev/pkgforge-go/github/gregorykogan/evo-layout/example?tag=HEAD-1507c08-250629T024941-riscv64-Linux&manifest",
  "portable": "true",
  "recurse_provides": "false",
  "shasum": "4340a747f698d2abb8d87bca421c6dbf4f111ea319bd6c54a307b4a0b4010157",
  "size": "2.1 MB",
  "size_raw": "2140776",
  "soar_syms": "false",
  "snapshots": [],
  "trusted": "true"
}
