{
  "_disabled": "false",
  "host": "riscv64-Linux",
  "rank": "",
  "pkg": "ghcr-cli",
  "pkg_family": "ghcr-cli",
  "pkg_id": "ghcr-cli#github.com_zinrai_ghcr_cli",
  "pkg_name": "ghcr-cli",
  "pkg_type": "static",
  "pkg_webpage": "https://github.com/zinrai/ghcr-cli",
  "bundle": "false",
  "category": [
    "Utility"
  ],
  "description": "No Description Provided",
  "homepage": [
    "https://github.com/zinrai/ghcr-cli"
  ],
  "license": [
    "Blessing"
  ],
  "maintainer": [
    "pkgforge-go (https://github.com/pkgforge-go/builder)"
  ],
  "provides": [
    "ghcr-cli"
  ],
  "note": [
    "[EXTERNAL] (This is an Official but externally maintained repository)",
    "This package was automatically built from source using go+zig",
    "Provided by: https://github.com/pkgforge-go/builder",
    "Learn More: https://docs.pkgforge.dev/repositories/external/pkgforge-go"
  ],
  "src_url": [
    "https://github.com/zinrai/ghcr-cli/archive/aaa3b180ce699cfc37b2b6b8921b4d7e126a1103.tar.gz"
  ],
  "tag": [
    "Utility"
  ],
  "version": "HEAD-aaa3b18-250220T172300",
  "version_upstream": "v0.1.0",
  "bsum": "ce729f1de41f3e914e7f23a846512e0e0ca8509fbb43bc20b98cf963bd95fda9",
  "build_date": "2025-06-22T22:15:37Z",
  "build_gha": "https://github.com/pkgforge-go/builder/actions/runs/15811074405",
  "build_id": "15811074405",
  "build_log": "https://api.ghcr.pkgforge.dev/pkgforge-go/github/zinrai/ghcr-cli/ghcr-cli?tag=HEAD-aaa3b18-250220T172300-riscv64-Linux&download=ghcr-cli.log",
  "deprecated": "false",
  "desktop_integration": "false",
  "download_count": "-1",
  "download_url": "https://api.ghcr.pkgforge.dev/pkgforge-go/github/zinrai/ghcr-cli/ghcr-cli?tag=HEAD-aaa3b18-250220T172300-riscv64-Linux&download=ghcr-cli",
  "external": "true",
  "ghcr_pkg": "ghcr.io/pkgforge-go/github/zinrai/ghcr-cli/ghcr-cli:HEAD-aaa3b18-250220T172300-riscv64-Linux",
  "ghcr_url": "https://ghcr.io/pkgforge-go/github/zinrai/ghcr-cli/ghcr-cli",
  "installable": "true",
  "manifest_url": "https://api.ghcr.pkgforge.dev/pkgforge-go/github/zinrai/ghcr-cli/ghcr-cli?tag=HEAD-aaa3b18-250220T172300-riscv64-Linux&manifest",
  "portable": "true",
  "recurse_provides": "false",
  "shasum": "5112fefb3b872a0362d040f8f0ef1be68148e09dd1bbaea13752fcb65448aa6d",
  "size": "4.3 MB",
  "size_raw": "4436360",
  "soar_syms": "false",
  "snapshots": [],
  "trusted": "true"
}
