{
  "_disabled": "false",
  "host": "x86_64-Linux",
  "rank": "",
  "pkg": "pathwalker",
  "pkg_family": "neuvector",
  "pkg_id": "pathwalker#github.com_neuvector_neuvector",
  "pkg_name": "pathwalker",
  "pkg_type": "static",
  "pkg_webpage": "https://github.com/neuvector/neuvector",
  "bundle": "false",
  "category": [
    "Utility"
  ],
  "description": "No Description Provided",
  "homepage": [
    "https://github.com/neuvector/neuvector"
  ],
  "license": [
    "Apache-2.0"
  ],
  "maintainer": [
    "pkgforge-go (https://github.com/pkgforge-go/builder)"
  ],
  "provides": [
    "agent",
    "pathwalker"
  ],
  "note": [
    "[EXTERNAL] (This is an Official but externally maintained repository)",
    "This package was automatically built from source using go+zig",
    "Provided by: https://github.com/pkgforge-go/builder",
    "Learn More: https://docs.pkgforge.dev/repositories/external/pkgforge-go"
  ],
  "src_url": [
    "https://github.com/neuvector/neuvector/archive/012bcfdafa7dd18872c563580588dccd9d253953.tar.gz"
  ],
  "tag": [
    "Utility"
  ],
  "version": "HEAD-012bcfd-250620T093615",
  "version_upstream": "",
  "bsum": "02f4944189a113160c5a9256cf3c464045c711be8bf7ac7a8f53812e550df685",
  "build_date": "2025-06-21T00:11:44Z",
  "build_gha": "https://github.com/pkgforge-go/builder/actions/runs/15789573390",
  "build_id": "15789573390",
  "build_log": "https://api.ghcr.pkgforge.dev/pkgforge-go/github/neuvector/neuvector/pathwalker?tag=HEAD-012bcfd-250620T093615-x86_64-Linux&download=pathwalker.log",
  "deprecated": "false",
  "desktop_integration": "false",
  "download_count": "1197",
  "download_url": "https://api.ghcr.pkgforge.dev/pkgforge-go/github/neuvector/neuvector/pathwalker?tag=HEAD-012bcfd-250620T093615-x86_64-Linux&download=pathwalker",
  "external": "true",
  "ghcr_pkg": "ghcr.io/pkgforge-go/github/neuvector/neuvector/pathwalker:HEAD-012bcfd-250620T093615-x86_64-Linux",
  "ghcr_url": "https://ghcr.io/pkgforge-go/github/neuvector/neuvector/pathwalker",
  "installable": "true",
  "manifest_url": "https://api.ghcr.pkgforge.dev/pkgforge-go/github/neuvector/neuvector/pathwalker?tag=HEAD-012bcfd-250620T093615-x86_64-Linux&manifest",
  "portable": "true",
  "recurse_provides": "false",
  "shasum": "16447a2008a71c7fdf6f59c00f59bc41ec43dd4987c891d18d0e6a7a255d3e3b",
  "size": "32 MB",
  "size_raw": "32512440",
  "soar_syms": "false",
  "snapshots": [],
  "trusted": "true"
}
