{
  "_disabled": "false",
  "host": "loongarch64-Linux",
  "rank": "",
  "pkg": "paperboy",
  "pkg_family": "paperboy",
  "pkg_id": "paperboy#github.com_rykov_paperboy",
  "pkg_name": "paperboy",
  "pkg_type": "static",
  "pkg_webpage": "https://github.com/rykov/paperboy",
  "bundle": "false",
  "category": [
    "Utility"
  ],
  "description": "💌💨 Email Campaign Delivery built with GoLang inspired by GoHugo",
  "homepage": [
    "https://github.com/rykov/paperboy"
  ],
  "license": [
    "Blessing"
  ],
  "maintainer": [
    "pkgforge-go (https://github.com/pkgforge-go/builder)"
  ],
  "provides": [
    "paperboy"
  ],
  "note": [
    "[EXTERNAL] (This is an Official but externally maintained repository)",
    "This package was automatically built from source using go+zig",
    "Provided by: https://github.com/pkgforge-go/builder",
    "Learn More: https://docs.pkgforge.dev/repositories/external/pkgforge-go"
  ],
  "src_url": [
    "https://github.com/rykov/paperboy/archive/2abfc6bd216df38366dc3386a168028c63304271.tar.gz"
  ],
  "tag": [
    "email",
    "email-campaigns",
    "email-marketing",
    "email-newsletter",
    "go",
    "html-emails",
    "paperboy"
  ],
  "version": "HEAD-2abfc6b-250623T223721",
  "version_upstream": "",
  "bsum": "5b083f27c43060c43d3fb2d006a42a6ded6569ab5ecb3672d5e95edad6a94f23",
  "build_date": "2025-06-24T03:30:29Z",
  "build_gha": "https://github.com/pkgforge-go/builder/actions/runs/15839733812",
  "build_id": "15839733812",
  "build_log": "https://api.ghcr.pkgforge.dev/pkgforge-go/github/rykov/paperboy/paperboy?tag=HEAD-2abfc6b-250623T223721-loongarch64-Linux&download=paperboy.log",
  "deprecated": "false",
  "desktop_integration": "false",
  "download_count": "497",
  "download_url": "https://api.ghcr.pkgforge.dev/pkgforge-go/github/rykov/paperboy/paperboy?tag=HEAD-2abfc6b-250623T223721-loongarch64-Linux&download=paperboy",
  "external": "true",
  "ghcr_pkg": "ghcr.io/pkgforge-go/github/rykov/paperboy/paperboy:HEAD-2abfc6b-250623T223721-loongarch64-Linux",
  "ghcr_url": "https://ghcr.io/pkgforge-go/github/rykov/paperboy/paperboy",
  "installable": "true",
  "manifest_url": "https://api.ghcr.pkgforge.dev/pkgforge-go/github/rykov/paperboy/paperboy?tag=HEAD-2abfc6b-250623T223721-loongarch64-Linux&manifest",
  "portable": "true",
  "recurse_provides": "false",
  "shasum": "c488873ff1a1c249f5251afee135041407307292b1e2e980aeff8197b1a764b7",
  "size": "20 MB",
  "size_raw": "20485168",
  "soar_syms": "false",
  "snapshots": [
    "HEAD-c4f0abc-250621T183142-loongarch64-Linux"
  ],
  "trusted": "true"
}
