[
  {
    "source": "pkgs_dump",
    "total": 6081
  },
  {
    "source": "pkgs_cli_only",
    "total": 5873
  },
  {
    "source": "pkgs_built",
    "total": 24363
  },
  {
    "source": "pkgs_built_unique",
    "total": 9440
  },
  {
    "source": "pkgs_queued",
    "total": 14244
  },
  {
    "source": "aarch64-Linux",
    "total": 23450
  },
  {
    "source": "loongarch64-Linux",
    "total": 22958
  },
  {
    "source": "riscv64-Linux",
    "total": 23602
  },
  {
    "source": "x86_64-Linux",
    "total": 23876
  },
  {
    "sum": "total-queued",
    "total": 66
  },
  {
    "sum": "total-built",
    "total": 93886
  }
]
