{
  "_disabled": "false",
  "host": "aarch64-Linux",
  "rank": "",
  "pkg": "headi",
  "pkg_family": "headi",
  "pkg_id": "headi#github.com_mlcsec_headi",
  "pkg_name": "headi",
  "pkg_type": "static",
  "pkg_webpage": "https://github.com/mlcsec/headi",
  "bundle": "false",
  "category": [
    "Utility"
  ],
  "description": "Customisable  and automated HTTP header injection",
  "homepage": [
    "https://github.com/mlcsec/headi"
  ],
  "license": [
    "Blessing"
  ],
  "maintainer": [
    "pkgforge-go (https://github.com/pkgforge-go/builder)"
  ],
  "provides": [
    "headi"
  ],
  "note": [
    "[EXTERNAL] (This is an Official but externally maintained repository)",
    "This package was automatically built from source using go+zig",
    "Provided by: https://github.com/pkgforge-go/builder",
    "Learn More: https://docs.pkgforge.dev/repositories/external/pkgforge-go"
  ],
  "src_url": [
    "https://github.com/mlcsec/headi/archive/3ae1f741321a43e2c365313c3d11b8f386054458.tar.gz"
  ],
  "tag": [
    "bugbounty",
    "golang",
    "header-injection"
  ],
  "version": "HEAD-3ae1f74-240627T122013",
  "version_upstream": "",
  "bsum": "aa0659672f30f52d2358001c3dec7b34216cfad73686697f30fbf0709b9825bd",
  "build_date": "2025-06-20T22:32:34Z",
  "build_gha": "https://github.com/pkgforge-go/builder/actions/runs/15788438466",
  "build_id": "15788438466",
  "build_log": "https://api.ghcr.pkgforge.dev/pkgforge-go/github/mlcsec/headi/headi?tag=HEAD-3ae1f74-240627T122013-aarch64-Linux&download=headi.log",
  "deprecated": "false",
  "desktop_integration": "false",
  "download_count": "253",
  "download_url": "https://api.ghcr.pkgforge.dev/pkgforge-go/github/mlcsec/headi/headi?tag=HEAD-3ae1f74-240627T122013-aarch64-Linux&download=headi",
  "external": "true",
  "ghcr_pkg": "ghcr.io/pkgforge-go/github/mlcsec/headi/headi:HEAD-3ae1f74-240627T122013-aarch64-Linux",
  "ghcr_url": "https://ghcr.io/pkgforge-go/github/mlcsec/headi/headi",
  "installable": "true",
  "manifest_url": "https://api.ghcr.pkgforge.dev/pkgforge-go/github/mlcsec/headi/headi?tag=HEAD-3ae1f74-240627T122013-aarch64-Linux&manifest",
  "portable": "true",
  "recurse_provides": "false",
  "shasum": "63813422f4f6298d93375137d07187657a72385085e555318967a345ebe717d9",
  "size": "5.6 MB",
  "size_raw": "5849856",
  "soar_syms": "false",
  "snapshots": [],
  "trusted": "true"
}
