{
  "_disabled": "false",
  "host": "loongarch64-Linux",
  "rank": "",
  "pkg": "session",
  "pkg_family": "cookies",
  "pkg_id": "session#github.com_goadesign_examples_cookies",
  "pkg_name": "session",
  "pkg_type": "static",
  "pkg_webpage": "https://goa.design",
  "bundle": "false",
  "category": [
    "Utility"
  ],
  "description": "Examples for goa showing specific capabilities",
  "homepage": [
    "https://goa.design"
  ],
  "license": [
    "MIT"
  ],
  "maintainer": [
    "pkgforge-go (https://github.com/pkgforge-go/builder)"
  ],
  "provides": [
    "session",
    "session-cli"
  ],
  "note": [
    "[EXTERNAL] (This is an Official but externally maintained repository)",
    "This package was automatically built from source using go+zig",
    "Provided by: https://github.com/pkgforge-go/builder",
    "Learn More: https://docs.pkgforge.dev/repositories/external/pkgforge-go"
  ],
  "src_url": [
    "https://proxy.golang.org/github.com/goadesign/examples/cookies/@v/v0.0.0-20250702025801-814d08ee0bb1.zip"
  ],
  "tag": [
    "Utility"
  ],
  "version": "v0.0.0-20250702025801-814d08ee0bb1",
  "version_upstream": "",
  "bsum": "d3d87f8ccfdf3db727d0387f8a04be998eabb3071a622949dc9986fb5df8a662",
  "build_date": "2025-07-11T18:49:26Z",
  "build_gha": "https://github.com/pkgforge-go/builder/actions/runs/16227300375",
  "build_id": "16227300375",
  "build_log": "https://api.ghcr.pkgforge.dev/pkgforge-go/github/goadesign/examples/cookies/session?tag=v0.0.0-20250702025801-814d08ee0bb1-loongarch64-Linux&download=session.log",
  "deprecated": "false",
  "desktop_integration": "false",
  "download_count": "198",
  "download_url": "https://api.ghcr.pkgforge.dev/pkgforge-go/github/goadesign/examples/cookies/session?tag=v0.0.0-20250702025801-814d08ee0bb1-loongarch64-Linux&download=session",
  "external": "true",
  "ghcr_pkg": "ghcr.io/pkgforge-go/github/goadesign/examples/cookies/session:v0.0.0-20250702025801-814d08ee0bb1-loongarch64-Linux",
  "ghcr_url": "https://ghcr.io/pkgforge-go/github/goadesign/examples/cookies/session",
  "installable": "true",
  "manifest_url": "https://api.ghcr.pkgforge.dev/pkgforge-go/github/goadesign/examples/cookies/session?tag=v0.0.0-20250702025801-814d08ee0bb1-loongarch64-Linux&manifest",
  "portable": "true",
  "recurse_provides": "false",
  "shasum": "3cab7a5fd28d42f56f9d2b1dae3786a57372ccf147c0ddd15b42da2a09b1b719",
  "size": "6.9 MB",
  "size_raw": "7176064",
  "soar_syms": "false",
  "snapshots": [],
  "trusted": "true"
}
