{
  "_disabled": "false",
  "host": "loongarch64-Linux",
  "rank": "",
  "pkg": "go",
  "pkg_family": "lapper",
  "pkg_id": "go#github.com_Finatext_lapper",
  "pkg_name": "go",
  "pkg_type": "static",
  "pkg_webpage": "https://github.com/Finatext/lapper",
  "bundle": "false",
  "category": [
    "Utility"
  ],
  "description": "Lapper is a wrapper programs for Container running on Lambda. _Beta_",
  "homepage": [
    "https://github.com/Finatext/lapper"
  ],
  "license": [
    "MIT"
  ],
  "maintainer": [
    "pkgforge-go (https://github.com/pkgforge-go/builder)"
  ],
  "provides": [
    "go",
    "lapper"
  ],
  "note": [
    "[EXTERNAL] (This is an Official but externally maintained repository)",
    "This package was automatically built from source using go+zig",
    "Provided by: https://github.com/pkgforge-go/builder",
    "Learn More: https://docs.pkgforge.dev/repositories/external/pkgforge-go"
  ],
  "src_url": [
    "https://github.com/Finatext/lapper/archive/254c2a6071c7e38d8ad935a92d35e2313a00d579.tar.gz"
  ],
  "tag": [
    "Utility"
  ],
  "version": "HEAD-254c2a6-250616T162826",
  "version_upstream": "",
  "bsum": "0d71eaf68d22b8e4f075f6d7c401f3bf7058cbe5075d6a6acb4b5bdcabfbdae2",
  "build_date": "2025-06-19T09:23:15Z",
  "build_gha": "https://github.com/pkgforge-go/builder/actions/runs/15753579091",
  "build_id": "15753579091",
  "build_log": "https://api.ghcr.pkgforge.dev/pkgforge-go/github/finatext/lapper/go?tag=HEAD-254c2a6-250616T162826-loongarch64-Linux&download=go.log",
  "deprecated": "false",
  "desktop_integration": "false",
  "download_count": "17",
  "download_url": "https://api.ghcr.pkgforge.dev/pkgforge-go/github/finatext/lapper/go?tag=HEAD-254c2a6-250616T162826-loongarch64-Linux&download=go",
  "external": "true",
  "ghcr_pkg": "ghcr.io/pkgforge-go/github/finatext/lapper/go:HEAD-254c2a6-250616T162826-loongarch64-Linux",
  "ghcr_url": "https://ghcr.io/pkgforge-go/github/finatext/lapper/go",
  "installable": "true",
  "manifest_url": "https://api.ghcr.pkgforge.dev/pkgforge-go/github/finatext/lapper/go?tag=HEAD-254c2a6-250616T162826-loongarch64-Linux&manifest",
  "portable": "true",
  "recurse_provides": "false",
  "shasum": "05cd491d4f9372a7f2fe297ea28370f62e23478bf17b4bb3fb422fa1d36bfb6c",
  "size": "1.6 MB",
  "size_raw": "1651320",
  "soar_syms": "false",
  "snapshots": [],
  "trusted": "true"
}
