{
  "_disabled": "false",
  "host": "aarch64-Linux",
  "rank": "",
  "pkg": "md2roff",
  "pkg_family": "md2roff",
  "pkg_id": "md2roff#github.com_davidnewhall_md2roff",
  "pkg_name": "md2roff",
  "pkg_type": "static",
  "pkg_webpage": "https://github.com/davidnewhall/md2roff",
  "bundle": "false",
  "category": [
    "Utility"
  ],
  "description": "Converts markdown files to unix man pages.",
  "homepage": [
    "https://github.com/davidnewhall/md2roff"
  ],
  "license": [
    "MIT"
  ],
  "maintainer": [
    "pkgforge-go (https://github.com/pkgforge-go/builder)"
  ],
  "provides": [
    "md2roff"
  ],
  "note": [
    "[EXTERNAL] (This is an Official but externally maintained repository)",
    "This package was automatically built from source using go+zig",
    "Provided by: https://github.com/pkgforge-go/builder",
    "Learn More: https://docs.pkgforge.dev/repositories/external/pkgforge-go"
  ],
  "src_url": [
    "https://github.com/davidnewhall/md2roff/archive/446b469632a396728ddab7edd7b9d2fc9da3d41e.tar.gz"
  ],
  "tag": [
    "Utility"
  ],
  "version": "HEAD-446b469-230113T000221",
  "version_upstream": "",
  "bsum": "831673b4dc2925750557c63aed4ca434f2c5c2d424d776c9ffbb48c2fe1190f7",
  "build_date": "2025-06-19T20:55:56Z",
  "build_gha": "https://github.com/pkgforge-go/builder/actions/runs/15765588901",
  "build_id": "15765588901",
  "build_log": "https://api.ghcr.pkgforge.dev/pkgforge-go/github/davidnewhall/md2roff/md2roff?tag=HEAD-446b469-230113T000221-aarch64-Linux&download=md2roff.log",
  "deprecated": "false",
  "desktop_integration": "false",
  "download_count": "6",
  "download_url": "https://api.ghcr.pkgforge.dev/pkgforge-go/github/davidnewhall/md2roff/md2roff?tag=HEAD-446b469-230113T000221-aarch64-Linux&download=md2roff",
  "external": "true",
  "ghcr_pkg": "ghcr.io/pkgforge-go/github/davidnewhall/md2roff/md2roff:HEAD-446b469-230113T000221-aarch64-Linux",
  "ghcr_url": "https://ghcr.io/pkgforge-go/github/davidnewhall/md2roff/md2roff",
  "installable": "true",
  "manifest_url": "https://api.ghcr.pkgforge.dev/pkgforge-go/github/davidnewhall/md2roff/md2roff?tag=HEAD-446b469-230113T000221-aarch64-Linux&manifest",
  "portable": "true",
  "recurse_provides": "false",
  "shasum": "7690ec0fcf55e163bad27eda4f982cfbdf33f4be7c612a7e6dba5e3f91e85297",
  "size": "3.5 MB",
  "size_raw": "3665880",
  "soar_syms": "false",
  "snapshots": [],
  "trusted": "true"
}
