{
  "_disabled": "false",
  "host": "riscv64-Linux",
  "rank": "",
  "pkg": "remove-dead-code",
  "pkg_family": "remove-dead-code",
  "pkg_id": "remove-dead-code#github.com_tmc_misc_remove_dead_code",
  "pkg_name": "remove-dead-code",
  "pkg_type": "static",
  "pkg_webpage": "https://github.com/tmc/misc",
  "bundle": "false",
  "category": [
    "Utility"
  ],
  "description": "Miscellaneous tools and codebases",
  "homepage": [
    "https://github.com/tmc/misc"
  ],
  "license": [
    "MIT"
  ],
  "maintainer": [
    "pkgforge-go (https://github.com/pkgforge-go/builder)"
  ],
  "provides": [
    "remove-dead-code"
  ],
  "note": [
    "[EXTERNAL] (This is an Official but externally maintained repository)",
    "This package was automatically built from source using go+zig",
    "Provided by: https://github.com/pkgforge-go/builder",
    "Learn More: https://docs.pkgforge.dev/repositories/external/pkgforge-go"
  ],
  "src_url": [
    "https://proxy.golang.org/github.com/tmc/misc/remove-dead-code/@v/v0.0.0-20250610033740-47096ee65a06.zip"
  ],
  "tag": [
    "Utility"
  ],
  "version": "v0.0.0-20250610033740-47096ee65a06",
  "version_upstream": "",
  "bsum": "b4633f1abbcc7c65c412d8c9e6bdf8177f6575cc88e0463d03f7e83c5d11a84f",
  "build_date": "2025-07-01T19:32:47Z",
  "build_gha": "https://github.com/pkgforge-go/builder/actions/runs/16007972439",
  "build_id": "16007972439",
  "build_log": "https://api.ghcr.pkgforge.dev/pkgforge-go/github/tmc/misc/remove-dead-code/remove-dead-code?tag=v0.0.0-20250610033740-47096ee65a06-riscv64-Linux&download=remove-dead-code.log",
  "deprecated": "false",
  "desktop_integration": "false",
  "download_count": "8",
  "download_url": "https://api.ghcr.pkgforge.dev/pkgforge-go/github/tmc/misc/remove-dead-code/remove-dead-code?tag=v0.0.0-20250610033740-47096ee65a06-riscv64-Linux&download=remove-dead-code",
  "external": "true",
  "ghcr_pkg": "ghcr.io/pkgforge-go/github/tmc/misc/remove-dead-code/remove-dead-code:v0.0.0-20250610033740-47096ee65a06-riscv64-Linux",
  "ghcr_url": "https://ghcr.io/pkgforge-go/github/tmc/misc/remove-dead-code/remove-dead-code",
  "installable": "true",
  "manifest_url": "https://api.ghcr.pkgforge.dev/pkgforge-go/github/tmc/misc/remove-dead-code/remove-dead-code?tag=v0.0.0-20250610033740-47096ee65a06-riscv64-Linux&manifest",
  "portable": "true",
  "recurse_provides": "false",
  "shasum": "a34d8161f823af977a083fe74027cd00319a7b1c703f5426bc459d142748d10d",
  "size": "5.2 MB",
  "size_raw": "5359496",
  "soar_syms": "false",
  "snapshots": [],
  "trusted": "true"
}
