{
  "_disabled": "false",
  "host": "x86_64-Linux",
  "rank": "",
  "pkg": "dnsupdater",
  "pkg_family": "dnsupdater",
  "pkg_id": "dnsupdater#github.com_brokenenso_dnsupdater",
  "pkg_name": "dnsupdater",
  "pkg_type": "static",
  "pkg_webpage": "https://github.com/brokenenso/dnsupdater",
  "bundle": "false",
  "category": [
    "Utility"
  ],
  "description": "Updates Cloudflare DNS with your NAT'ed (external ip) address",
  "homepage": [
    "https://github.com/brokenenso/dnsupdater"
  ],
  "license": [
    "non-standard"
  ],
  "maintainer": [
    "pkgforge-go (https://github.com/pkgforge-go/builder)"
  ],
  "provides": [
    "dnsupdater"
  ],
  "note": [
    "[EXTERNAL] (This is an Official but externally maintained repository)",
    "This package was automatically built from source using go+zig",
    "Provided by: https://github.com/pkgforge-go/builder",
    "Learn More: https://docs.pkgforge.dev/repositories/external/pkgforge-go"
  ],
  "src_url": [
    "https://proxy.golang.org/github.com/brokenenso/dnsupdater/@v/v0.0.0-20250508135817-e7ab49934159.zip"
  ],
  "tag": [
    "Utility"
  ],
  "version": "v0.0.0-20250508135817-e7ab49934159",
  "version_upstream": "",
  "bsum": "61306953772c258a78f693b1cc3a51b745eb70380aaa6b49a726aa49bca8995c",
  "build_date": "2025-07-06T04:22:23Z",
  "build_gha": "https://github.com/pkgforge-go/builder/actions/runs/16095144429",
  "build_id": "16095144429",
  "build_log": "https://api.ghcr.pkgforge.dev/pkgforge-go/github/brokenenso/dnsupdater/dnsupdater?tag=v0.0.0-20250508135817-e7ab49934159-x86_64-Linux&download=dnsupdater.log",
  "deprecated": "false",
  "desktop_integration": "false",
  "download_count": "-1",
  "download_url": "https://api.ghcr.pkgforge.dev/pkgforge-go/github/brokenenso/dnsupdater/dnsupdater?tag=v0.0.0-20250508135817-e7ab49934159-x86_64-Linux&download=dnsupdater",
  "external": "true",
  "ghcr_pkg": "ghcr.io/pkgforge-go/github/brokenenso/dnsupdater/dnsupdater:v0.0.0-20250508135817-e7ab49934159-x86_64-Linux",
  "ghcr_url": "https://ghcr.io/pkgforge-go/github/brokenenso/dnsupdater/dnsupdater",
  "installable": "true",
  "manifest_url": "https://api.ghcr.pkgforge.dev/pkgforge-go/github/brokenenso/dnsupdater/dnsupdater?tag=v0.0.0-20250508135817-e7ab49934159-x86_64-Linux&manifest",
  "portable": "true",
  "recurse_provides": "false",
  "shasum": "e35c114bbd934926823dae6dd088f108f784ac6b64ce4044270d6808aab1cb53",
  "size": "7.8 MB",
  "size_raw": "8163088",
  "soar_syms": "false",
  "snapshots": [],
  "trusted": "true"
}
